signalfx/__init__.py
signalfx/constants.py
signalfx/version.py
signalfx/signalflow/__init__.py
signalfx/signalflow/channel.py
signalfx/signalflow/computation.py
signalfx/signalflow/errors.py
signalfx/signalflow/messages.py
signalfx/signalflow/sse.py
signalfx/signalflow/transport.py
signalfx/signalflow/ws.py
signalflow_client_python-1.3.7.dist-info/METADATA
signalflow_client_python-1.3.7.dist-info/WHEEL
signalflow_client_python-1.3.7.dist-info/licenses/LICENSE.txt
signalflow_client_python-1.3.7.dist-info/RECORD
