Metadata-Version: 2.4
Name: signalflow-client-python
Version: 1.3.7
Project-URL: Documentation, https://github.com/signalfx/signalflow-client-python#readme
Project-URL: Issues, https://github.com/signalfx/signalflow-client-python/issues
Project-URL: Source, https://github.com/signalfx/signalflow-client-python
Author-email: Splunk <splunk-oss@splunk.com>
License-Expression: Apache-2.0
License-File: LICENSE.txt
Classifier: Development Status :: 4 - Beta
Classifier: Programming Language :: Python
Classifier: Programming Language :: Python :: 3.8
Classifier: Programming Language :: Python :: 3.9
Classifier: Programming Language :: Python :: 3.10
Classifier: Programming Language :: Python :: 3.11
Classifier: Programming Language :: Python :: 3.12
Classifier: Programming Language :: Python :: Implementation :: CPython
Classifier: Programming Language :: Python :: Implementation :: PyPy
Requires-Python: >=3.8
Requires-Dist: certifi
Requires-Dist: protobuf<5.0.0,>=4.25.8
Requires-Dist: pyformance>=0.3.1
Requires-Dist: six>=1.6.0
Requires-Dist: sseclient-py>=1.4
Requires-Dist: urllib3>=2.5.0
Requires-Dist: ws4py>=0.4.1
